airflow_providers_rdb_to_kudu/RDBToKuduSyncOperator.py
airflow_providers_rdb_to_kudu/__init__.py
airflow_providers_rdb_to_kudu-0.1.0.dist-info/METADATA
airflow_providers_rdb_to_kudu-0.1.0.dist-info/WHEEL
airflow_providers_rdb_to_kudu-0.1.0.dist-info/top_level.txt
airflow_providers_rdb_to_kudu-0.1.0.dist-info/RECORD
